app/__init__.py
app/edcode.py
edcode-1.1.dist-info/METADATA
edcode-1.1.dist-info/WHEEL
edcode-1.1.dist-info/entry_points.txt
edcode-1.1.dist-info/top_level.txt
edcode-1.1.dist-info/RECORD
