Metadata-Version: 2.4
Name: edcode
Version: 1.1
Dynamic: description
Dynamic: description-content-type
